{
    "intents": [
        {
            "tag": "deactivate",
            "patterns": [
                "deactivate",
                "deactivate",
                "sleep mode",
                "sleep mode ",
                "offline",
                "take a nap",
                "shut up",
                "turn off",
                "turn off",
                "turn yourself off",
                "shut up your mouth",
                "will you shutup",
                "stop taking",
                "be silent",
                "silent please"
            ],
            "response": [
                "ok sir",
                "command mode off",
                "deactivating",
                "ok im off"
            ]
        },
        {
            "tag": "take note",
            "patterns": [
                "stake a note",
                "mark this note",
                "mark this todo",
                "store this note",
                "store this todo",
                "make a note",
                "create a note",
                "take this note",
                "make a note for me",
                "make a todo"
            ],
            "response": [
                "ok"
            ]
        },
        {
            "tag": "find solutions",
            "patterns": [
                "find solution for this error",
                "help me with this error",
                "help me to find this error",
                "find solutions for this error",
                "give me the solutions for this error"
            ],
            "response": [
                "sure sir",
                "ok sir"
            ]
        },
        {
            "tag": "open websites",
            "patterns": [
                "open instagram",
                "open twitter",
                "open github",
                "open google",
                "open facebook",
                "visit google",
                "visit instagram",
                "visit twitter",
                "visit github",
                "visit google",
                "goto instagram"
            ],
            "response": [
                "ok sir"
            ]
        },
        {
            "tag": "wikipeadia",
            "patterns": [
                "what is google",
                "what is google",
                "tell me about youtube",
                "tell me about youtube",
                "what is",
                "what is",
                "tell me about",
                "who is",
                "who is"
            ],
            "response": [
                "ok, wait sir",
                "ok, let me check"
            ]
        },
        {
            "tag": "create repository",
            "patterns": [
                "make a new repo",
                "make a new repository in github",
                "make a new project in github",
                "create a new repo",
                "create a new repository in github",
                "create a new project in github",
                "i want to make a new project",
                "can you make a project for me please"
            ],
            "response": [
                "hmm",
                "ok",
                "ok sir"
            ]
        },
        {
            "tag": "web search prompt",
            "patterns": [
                "open search box",
                "give me the search box",
                "open the prompt",
                "open a search prompt",
                "open a search box",
                "give me the search box",
                "i want to search"
            ],
            "response": [
                "opening search prompt.."
            ]
        },
        {
            "tag": "clone repository",
            "patterns": [
                "clone this repo",
                "clone this project",
                "download this repo",
                "download this project",
                "clone this repository",
                "download this repository"
            ],
            "response": [
                "ok cloning the repository",
                "ok downloading the repository"
            ]
        },
        {
            "tag": "take screenshot",
            "patterns": [
                "take a screenshot",
                "capture the screenshot",
                "screenshot this",
                "take this picture",
                "capture this picture",
                "save this picture",
                "take a photo of it",
                "screen shot"
            ],
            "response": [
                "ok sir",
                "ok"
            ]
        },
        {
            "tag": "exit",
            "patterns": [
                "exit",
                "close yourself",
                "close your self",
                "close",
                "terminate yourself",
                "terminate",
                "shutdown please",
                "shutdown yourself"
            ],
            "response": [
                "program terminating",
                "exiting program",
                "closing"
            ]
        },
        {
            "tag": "spotify",
            "patterns": [
                "open spotify",
                "open spotify",
                "open spotify",
                "play music",
                "play a song",
                "play me some song",
                "play some song",
                "i want hear song",
                "i want to hear music"
            ],
            "response": [
                "ok sir",
                "opening spotify"
            ]
        },
        {
            "tag": "start writing",
            "patterns": [
                "write something for me",
                "write this",
                "start writing",
                "write this for me",
                "start writing",
                "activate writing mode",
                "i want to write something"
            ],
            "response": [
                "ok sir",
                "ok writing mode on",
                "ok tell me what you want to write"
            ]
        },
        {
            "tag": "text translation",
            "patterns": [
                "can you translate a word for me",
                "translate this",
                "translate this",
                "translate",
                "translate",
                "the meaning of",
                "the meaning of",
                "is mean by",
                "is mean by"
            ],
            "response": [
                "ok"
            ]
        }
    ]
}